httpx_structlog/__init__.py
httpx_structlog/client.py
httpx_structlog/py.typed
httpx_structlog/transport.py
httpx_structlog-0.1.1.dist-info/METADATA
httpx_structlog-0.1.1.dist-info/WHEEL
httpx_structlog-0.1.1.dist-info/RECORD
