Metadata-Version: 2.1
Name: httpx-structlog
Version: 0.1.1
Summary: Сustom httpx client that logs all requests and responses with structlog.
Home-page: https://github.com/r-m-n/httpx-structlog
Keywords: httpx,structlog,logging
Author: Your Name
Author-email: you@example.com
Requires-Python: >=3.8,<4.0
Classifier: Programming Language :: Python :: 3
Classifier: Programming Language :: Python :: 3.8
Classifier: Programming Language :: Python :: 3.9
Classifier: Programming Language :: Python :: 3.10
Classifier: Programming Language :: Python :: 3.11
Classifier: Programming Language :: Python :: 3.12
Classifier: Programming Language :: Python :: 3.13
Requires-Dist: httpx (>=0.27.0,<0.28.0)
Requires-Dist: structlog (>=24.2.0,<25.0.0)
Project-URL: Repository, https://github.com/r-m-n/httpx-structlog
